ext_http_server.py
setup.py
ext_http_server.egg-info/PKG-INFO
ext_http_server.egg-info/SOURCES.txt
ext_http_server.egg-info/dependency_links.txt
ext_http_server.egg-info/entry_points.txt
ext_http_server.egg-info/top_level.txt