Metadata-Version: 1.0
Name: ext-http-server
Version: 0.2
Summary: An extended version of python's SimpleHTTPServer that supports https, authentication, rate limiting, and download resuming.
Home-page: https://github.com/bboe/extended_http_server
Author: Bryce Boe
Author-email: bbzbryce@gmail.com
License: UNKNOWN
Keywords: http resume,http rate limit,http authentication
Platform: UNKNOWN
